dagster_graphql/__init__.py
dagster_graphql/cli.py
dagster_graphql/py.typed
dagster_graphql/version.py
dagster_graphql/client/__init__.py
dagster_graphql/client/client.py
dagster_graphql/client/client_queries.py
dagster_graphql/client/query.py
dagster_graphql/client/utils.py
dagster_graphql/implementation/__init__.py
dagster_graphql/implementation/events.py
dagster_graphql/implementation/external.py
dagster_graphql/implementation/fetch_asset_checks.py
dagster_graphql/implementation/fetch_asset_condition_evaluations.py
dagster_graphql/implementation/fetch_assets.py
dagster_graphql/implementation/fetch_auto_materialize_asset_evaluations.py
dagster_graphql/implementation/fetch_backfills.py
dagster_graphql/implementation/fetch_env_vars.py
dagster_graphql/implementation/fetch_instigators.py
dagster_graphql/implementation/fetch_logs.py
dagster_graphql/implementation/fetch_partition_sets.py
dagster_graphql/implementation/fetch_partition_subsets.py
dagster_graphql/implementation/fetch_pipelines.py
dagster_graphql/implementation/fetch_resources.py
dagster_graphql/implementation/fetch_runs.py
dagster_graphql/implementation/fetch_schedules.py
dagster_graphql/implementation/fetch_sensors.py
dagster_graphql/implementation/fetch_solids.py
dagster_graphql/implementation/fetch_ticks.py
dagster_graphql/implementation/loader.py
dagster_graphql/implementation/partition_status_utils.py
dagster_graphql/implementation/run_config_schema.py
dagster_graphql/implementation/telemetry.py
dagster_graphql/implementation/utils.py
dagster_graphql/implementation/execution/__init__.py
dagster_graphql/implementation/execution/backfill.py
dagster_graphql/implementation/execution/dynamic_partitions.py
dagster_graphql/implementation/execution/launch_execution.py
dagster_graphql/implementation/execution/run_lifecycle.py
dagster_graphql/schema/__init__.py
dagster_graphql/schema/asset_checks.py
dagster_graphql/schema/asset_condition_evaluations.py
dagster_graphql/schema/asset_graph.py
dagster_graphql-1.12.13.dist-info/licenses/LICENSE
dagster_graphql-1.12.13.dist-info/METADATA
dagster_graphql-1.12.13.dist-info/WHEEL
dagster_graphql-1.12.13.dist-info/entry_points.txt
dagster_graphql-1.12.13.dist-info/top_level.txt
dagster_graphql-1.12.13.dist-info/RECORD
